gashokoru_web/__init__.py
gashokoru_web/app.py
gashokoru_web/api/__init__.py
gashokoru_web/api/api.py
gashokoru_web/api/routes/__init__.py
gashokoru_web/api/routes/_rules.py
gashokoru_web/api/routes/admin.py
gashokoru_web/api/routes/errors.py
gashokoru_web/api/routes/user.py
gashokoru_web/config/__init__.py
gashokoru_web/config/config.py
gashokoru_web/front/__init__.py
gashokoru_web/front/_static/__init__.py
gashokoru_web/front/templates/__init__.py
gashokoru_web-0.2.4.dist-info/METADATA
gashokoru_web-0.2.4.dist-info/WHEEL
gashokoru_web-0.2.4.dist-info/entry_points.txt
gashokoru_web-0.2.4.dist-info/top_level.txt
gashokoru_web-0.2.4.dist-info/RECORD
